pupillib/__init__.py
pupillib/example_only_get_marker_positions.py
pupillib/example_xdf_to_csv.py
pupillib/pupil_lib.py
pupillib/simple_script.py
pupillib/simple_script_pupil_lsl_relay_v2.py
pupillib/core/__init__.py
pupillib/core/data_container.py
pupillib/core/plib_parser.py
pupillib/core/starter.py
pupillib/core/utilities/MPLogger.py
pupillib/core/utilities/__init__.py
pupillib/core/utilities/config_store.py
pupillib/core/utilities/default_dataset_processors.py
pupillib/core/utilities/utilities.py
pupillib/core/workers/__init__.py
pupillib/core/workers/dataset_worker.py
pupillib/core/workers/eye_worker.py
pupillib/core/workers/generic_eye_level_worker.py
pupillib/core/workers/post_worker.py
pupillib/core/workers/trial_worker.py
pupillib/core/workers/trigger_worker.py
pupillib/core/workers/processors/__init__.py
pupillib/core/workers/processors/dataset_processor.py
pupillib/core/workers/processors/decorator_registrar.py
pupillib/core/workers/processors/eye_processor.py
pupillib/core/workers/processors/generic_eye_level_processor.py
pupillib/core/workers/processors/runner_processor.py
pupillib/core/workers/processors/trial_processor.py
pupillib/core/workers/processors/trigger_processor.py
pupillib/core/workers/processors/xdfloader_processor.py
pupillib/core/workers/processors/processing_functions/__init__.py
pupillib/core/workers/processors/processing_functions/testing_functions.py
pupillib/dependencies/__init__.py
pupillib/dependencies/xdf/__init__.py
pupillib/dependencies/xdf/make_release.py
pupillib/dependencies/xdf/Python/__init__.py
pupillib/dependencies/xdf/Python/xdf.py
pupillib-1.2.1.dist-info/LICENSE
pupillib-1.2.1.dist-info/METADATA
pupillib-1.2.1.dist-info/WHEEL
pupillib-1.2.1.dist-info/entry_points.txt
pupillib-1.2.1.dist-info/top_level.txt
pupillib-1.2.1.dist-info/RECORD
