Metadata-Version: 2.1
Name: pupillib
Version: 1.2.1
Summary: A software package to perform trial extraction on Pupil Labs eye tracker data collected into XDF files through LabRecorder.
Home-page: https://github.com/gmierz/pupil-lib-python/
Author: Gregory Mierzwinski
Author-email: gmierz1@live.ca
License: GPLv3
Keywords: trial extraction pupil labs
Platform: UNKNOWN
Classifier: Programming Language :: Python :: 3
Classifier: License :: OSI Approved :: GNU General Public License v3 (GPLv3)
Classifier: Operating System :: OS Independent
Classifier: Development Status :: 5 - Production/Stable
Classifier: Topic :: Scientific/Engineering :: Visualization
Classifier: Topic :: Scientific/Engineering :: Medical Science Apps.
Classifier: Topic :: Scientific/Engineering :: Information Analysis
Classifier: Topic :: Scientific/Engineering
Requires-Dist: msgpack
Requires-Dist: frozendict
Requires-Dist: cycler
Requires-Dist: matplotlib
Requires-Dist: numpy
Requires-Dist: pip
Requires-Dist: pyparsing
Requires-Dist: python-dateutil
Requires-Dist: pytz
Requires-Dist: ruamel.yaml
Requires-Dist: six
